mkpipe_extractor_mysql/__init__.py
mkpipe_extractor_mysql/jars/mysql-connector-j-9.1.0.jar
mkpipe_extractor_mysql/jars/oci-java-sdk-common-3.41.2.jar
mkpipe_extractor_mysql/jars/protobuf-java-4.26.1.jar
mkpipe_extractor_mysql-0.2.0.dist-info/licenses/LICENSE
mkpipe_extractor_mysql-0.2.0.dist-info/METADATA
mkpipe_extractor_mysql-0.2.0.dist-info/WHEEL
mkpipe_extractor_mysql-0.2.0.dist-info/entry_points.txt
mkpipe_extractor_mysql-0.2.0.dist-info/top_level.txt
mkpipe_extractor_mysql-0.2.0.dist-info/RECORD
